Metadata-Version: 1.1
Name: django-rest-swagger-enhancer
Version: 0.0.2
Summary: Django REST Swagger enhancement
Home-page: https://github.com/eshandas/django_rest_swagger_enhancer
Author: Eshan Das
Author-email: eshandasnit@gmail.com
License: UNKNOWN
Download-URL: https://github.com/eshandas/django_rest_swagger_enhancer/archive/0.0.2.tar.gz
Keywords: django,django rest framework,swagger,django rest swagger
Platform: UNKNOWN
